pybotfinder/__init__.py
pybotfinder/bot_detection_model.pkl
pybotfinder/cli.py
pybotfinder/collector.py
pybotfinder/feature_extractor.py
pybotfinder/model_trainer.py
pybotfinder/predictor.py
pybotfinder-0.3.2.dist-info/licenses/LICENSE
pybotfinder-0.3.2.dist-info/METADATA
pybotfinder-0.3.2.dist-info/WHEEL
pybotfinder-0.3.2.dist-info/entry_points.txt
pybotfinder-0.3.2.dist-info/top_level.txt
pybotfinder-0.3.2.dist-info/RECORD
